RV32IMFcore/DivFPU_Flowchart.v
module DivFPU_Flowchart (
    input  [31:0] N1,
    input  [31:0] N2,
    output [31:0] result
);

    // Internal variables
    reg [23:0] M1, M2;
    reg [24:0] M;        // Mantissa result after division
    reg [8:0] E;
    reg [47:0] raw_mant;
    reg [22:0] mantissa;
    reg [7:0] exponent;
    reg Sign;
    wire [7:0] E1, E2;
    wire S1, S2;
    integer i;

    assign E1 = N1[30:23];
    assign E2 = N2[30:23];
    assign S1 = N1[31];
    assign S2 = N2[31];

    always @(*) begin
        // Step 1: Compute Sign
        Sign = S1 ^ S2;

        // Step 2: Extract mantissas with hidden bit
        M1 = {1'b1, N1[22:0]};
        M2 = {1'b1, N2[22:0]};

        // Step 3: Subtract exponents and add bias
        E = E1 - E2 + 127;

        // Step 4: Fixed-point division (scaled)
        raw_mant <= {M1,23'b0};
        M = raw_mant / M2;  // 47-bit numerator


        // Step 5: Zero check
        if (M == 0) begin
            E = 8'd0;
            mantissa = 23'd0;
        end else begin
            if (M[24]) begin
                M = M >> 1;
                E = E + 1;
            end
            // Step 6: Normalize using a for loop
            else begin
            for (i = 0;!M[23] && E > 0 && i < 23; i = i + 1) begin
                M = M << 1;
                E = E - 1;
            end
            end

            // Step 7: Check for exponent overflow
            if (E[8]) begin
                exponent = 8'hFF;
                mantissa = 23'd0;
            end else begin
                exponent = E[7:0];
                mantissa = M; // Extract top 23 bits
            end
        end
    end

    assign result = {Sign, exponent, mantissa};

endmodule

RV32IMFcore/MulFPU.v
module MulFPU (
    input [31:0] N1,
    input [31:0] N2,
    output [31:0]result
);

//paramter for preporcessing
reg [23:0] M1 , M2;
reg [7:0] E1, E2;
reg S1, S2;
integer i;
//parameter for temporary resullt
reg [47:0] M;
reg [8:0] E;
// parameter for final result
reg [22:0] mantissa;
reg [7:0] exponent;
reg Sign;

always @ (*) begin
// Initiialize the values
    M1 = {1'b1,N1[22:0]};
    M2 = {1'b1,N2[22:0]};

    E1 = N1[30:23];
    E2 = N2[30:23];

    S1 = N1[31];
    S2 = N2[31];

// compute sign 
    Sign = S1 ^ S2;

// Add E1 from E2
    E = E1 + E2 - 127;

// Multiply M1 and M2
    M = M1 * M2;
    // check for M overflows
    if (M == 0)
        E = 0;
    // check if there is is a carry
    else if (M[47]) begin
        M = M >> 1;
        E = E + 1;
    end
    else begin 
        // normalize the value
        for (i = 0; M[46] !== 1'b1 && E > 0 && i < 47; i = i + 1) begin
             M = M << 1;
             E = E - 1;
         end
    end

    //check for exponent overflow
    if (E[8])
        E[7:0] = 8'hFF;
    //final result for mantissa and exponent
    mantissa = M[45:23];
    exponent = E[7:0];
end

assign result = {Sign, exponent, mantissa};

endmodule

FPU_pipeline/src/AddSubFPU.v
`define FPU_ADD 1'b0
`define FPU_SUB 1'b1 

module AddSubFPU (
    input [31:0] N1,
    input [31:0] N2,
    input sel,
    output [31:0] result
);

//parameter for comparison
reg [31:0] N1_swap, N2_swap;
//paramter for preporcessing
reg [7:0] E1, E2;
reg [7:0] d;
//parameter for temporary resullt
reg [23:0] S1 , S2;
reg sign1, sign2;
reg carry;
reg [23:0] temp_mantissa;
// parameter for final result
reg [22:0] mantissa;
reg [7:0] exponent;
reg Sign;

integer i;

always @(*)
begin

N1_swap = N1;
N2_swap = N2;

// Is E1 =  0
if (N1[31:23] == 0)
    S1[23] = 1'b0;
//is E2 = 0
if (N2[31:23] == 0)
    S2[23] = 1'b0;

//Is E2 greater than E1? Yes(swap) : No(Dont swap) 
if (N2[30:23] > N1[30:23]) 
    begin
        N1_swap = N2;
        N2_swap = N1;
    end
else
    begin
        N1_swap = N1;
        N2_swap = N2;
    end        

//assign to the temporary values
S1 = {1'b1, N1_swap[22:0]};
S2 = {1'b1, N2_swap[22:0]};
sign1 = N1_swap[31];
sign2 = N2_swap[31];
E1 = N1_swap[30:23];
E2 = N2_swap[30:23];

//shifting by d
d = E1 - E2;
S2 = (d > 0)? (S2 >> d) : S2;
E2 = E2 + d;
exponent = E1;

case(sel)
    `FPU_ADD :{carry,temp_mantissa} = (sign1 ~^ sign2)? (S1 + S2) : (S1 - S2);
    `FPU_SUB : begin
                {carry,temp_mantissa} = (sign1 ~^ sign2)? S1 - S2 : S1 + S2;
                if (N2[30:23] > N1[30:23]) sign1 = ~sign1;
    end
     //default :temp_mantissa = 23'b0;
endcase

// check for the 1.xxxx format in mantissa
if(carry)
    begin
        temp_mantissa = temp_mantissa>>1;
        exponent = (exponent < 8'hff) ? exponent + 1 : 8'hff;  // protect exponent overflow
    end
else if(|temp_mantissa != 1'b1)  // mantissa contains no 1 or unknown value (result should be 0)
    begin
        temp_mantissa = 0;
    end
else
    begin
        // 1st bit is not 1, but there is some 1 in the mantissa (protecting exponent underflow)
        // fixed limit of iterations because Vivado saw this as an infinite loop
        for(i = 0; temp_mantissa[23] !== 1'b1 && exponent > 0 && i < 24; i = i + 1) begin
            temp_mantissa = temp_mantissa << 1;
            exponent = exponent - 1;
        end
    end
end

assign result = {sign1,exponent,temp_mantissa[22:0]};

endmodule

FPU/src/FPU.v
`timescale 1ns / 1ps



`define FPU_ADDSUB   3'b000, 3'b001
`define FPU_MUL      3'b010
`define FPU_DIV      3'b011
`define SIGN_INJECTION  3'b100

module FPU(
    input [31:0] rs1,
    input [31:0] rs2,
    input [2:0] fpu_control,
    input [2:0] funct3,
    input fpu_sel,
    output reg [31:0] fpu_result
    );

    // temporary results for fpu operations
    wire [31:0] AddSubResult;
    wire [31:0] MulResult;
    wire [31:0] DivResult;
    wire [31:0] SqrtResult;
    wire sign_temp;

    assign sign_temp = rs1[31] ^ rs2[31];

    //module instantiation
    AddSubFPU ASFPU_inst (.N1(rs1), .N2(rs2), .sel(fpu_sel), .result(AddSubResult));
    MulFPU MulFPUinst(.N1(rs1),.N2(rs2),.result(MulResult));
    DivFPU_Flowchart DivFPUinst(.N1(rs1), .N2(rs2), .result(DivResult));

    always @(*) begin
        case(fpu_control) 
            `FPU_ADDSUB: fpu_result = AddSubResult;
            `FPU_MUL: fpu_result = MulResult;
            `FPU_DIV: fpu_result = DivResult;
            `SIGN_INJECTION: begin
                case(funct3)
                    3'b000:fpu_result = {rs2[31],rs1[30:0]} ;
                    3'b010:fpu_result = {sign_temp,rs1[30:0]};
                endcase
            end
            default:    
                fpu_result = 32'b0;
    endcase
    end

endmodule

FPU/tb/FPU_tb.v
`include "../src/FPU.v"

`include "../../FPU/src/DivFPU_Flowchart.v"
`include "../../FPU/src/MulFPU.v"
`include "../../FPU/src/AddSubFPU.v"
module FPU_tb;
reg [31:0] A,B;
reg fpu_sel;
reg [2:0] fpu_control;
reg [2:0] funct3;
wire [31:0] result;
real  value; 
FPU dut (
    .rs1(A),
    .rs2(B),
    .fpu_control(fpu_control),
    .funct3(funct3),
    .fpu_sel(fpu_sel),
    .fpu_result(result)
);

initial  
begin
        $dumpfile("FPU.vcd");
        $dumpvars(0,FPU_tb);
//addition
A = 32'b0_10000000_10011001100110011001100;  // 3.2
B = 32'b0_10000001_00001100110011001100110;  // 4.2
fpu_control = 3'b000;
fpu_sel = 1'b0;
#20
A = 32'b0_01111110_01010001111010111000011;  // 0.66
B = 32'b0_01111110_00000101000111101011100;  // 0.51
fpu_control = 3'b000;
fpu_sel = 1'b0;
#20
A = 32'b1_01111110_00000000000000000000000;  // -0.5
B = 32'b1_10000001_10011001100110011001100;  // -6.4
fpu_control = 3'b000;
fpu_sel = 1'b0;
#20
A = 32'b1_01111110_00000000000000000000000;  // -0.5
B = 32'b0_10000001_10011001100110011001100;  //  6.4
fpu_control = 3'b000;
fpu_sel = 1'b0;
#20
A = 32'h4034b4b5;
B = 32'hbf70f0f1;
fpu_control = 3'b000;
fpu_sel = 1'b0;
//subtraction
#20
A = 32'b0_10000000_10011001100110011001100;  // 3.2
B = 32'b0_10000001_00001100110011001100110;  // 4.2
fpu_control = 3'b001;
fpu_sel = 1'b1;
#20
A = 32'b0_01111110_01010001111010111000011;  // 0.66
B = 32'b0_01111110_00000101000111101011100;  // 0.51
fpu_control = 3'b001;
fpu_sel = 1'b1;
#20
A = 32'b1_01111110_00000000000000000000000;  // -0.5
B = 32'b1_10000001_10011001100110011001100;  // -6.4
fpu_control = 3'b001;
fpu_sel = 1'b1;
#20
A = 32'b1_01111110_00000000000000000000000;  // -0.5
B = 32'b0_10000001_10011001100110011001100;  //  6.4
fpu_control = 3'b001;
fpu_sel = 1'b1;
#20
A = 32'h4034b4b5;
B = 32'hbf70f0f1;
fpu_control = 3'b001;
fpu_sel = 1'b1;
//Multiplication
#20
A = 32'b0_10000000_10011001100110011001100;  // 3.2
B = 32'b0_10000001_00001100110011001100110;  // 4.2
fpu_control = 3'b010;
#20
A = 32'b0_01111110_01010001111010111000011;  // 0.66
B = 32'b0_01111110_00000101000111101011100;  // 0.51
fpu_control = 3'b010;
#20
A = 32'b1_01111110_00000000000000000000000;  // -0.5
B = 32'b1_10000001_10011001100110011001100;  // -6.4
fpu_control = 3'b010;
#20
A = 32'b1_01111110_00000000000000000000000;  // -0.5
B = 32'b0_10000001_10011001100110011001100;  //  6.4
fpu_control = 3'b010;
#20
A = 32'h4034b4b5;
B = 32'hbf70f0f1;
fpu_control = 3'b010;
//Division
#20
B = 32'b0_10000000_10011001100110011001100;  // 3.2
A = 32'b0_10000001_00001100110011001100110;  // 4.2
fpu_control = 3'b011;
#20
A = 32'b0_01111110_01010001111010111000011;  // 0.66
B = 32'b0_01111110_00000101000111101011100;  // 0.51
fpu_control = 3'b011;
#20
B = 32'b1_01111110_00000000000000000000000;  // -0.5
A = 32'b1_10000001_10011001100110011001100;  // -6.4
fpu_control = 3'b011;
#20
A = 32'b1_01111110_00000000000000000000000;  // -0.5
B = 32'b0_10000001_10011001100110011001100;  //  6.4
fpu_control = 3'b011;
#20
A = 32'h4034b4b5;
B = 32'hbf70f0f1;
fpu_control = 3'b011;
#20

//sign injections
A = 32'b1_01111110_00000000000000000000000;  // -0.5
B = 32'b0_10000001_10011001100110011001100;  //  6.4
fpu_control = 3'b100;
funct3 = 3'b000;
#20
A = 32'b1_01111110_00000000000000000000000;  // -0.5
B = 32'b0_10000001_10011001100110011001100;  //  6.4
fpu_control = 3'b100;
funct3 = 3'b010;

end

initial
begin
#15
$display("===== Addition =====");
value =(2**(result[30:23]-127))*($itor({1'b1,result[22:0]})/2**23)*((-1)**(result[31]));
$display("Expected Value : %f Result : %f",3.2+4.2,value);
#20
value =(2**(result[30:23]-127))*($itor({1'b1,result[22:0]})/2**23)*((-1)**(result[31]));
$display("Expected Value : %f Result : %f",0.66+0.51,value);
#20
value =(2**(result[30:23]-127))*($itor({1'b1,result[22:0]})/2**23)*((-1)**(result[31]));
$display("Expected Value : %f Result : %f",-0.5+(-6.4),value);
#20
value =(2**(result[30:23]-127))*($itor({1'b1,result[22:0]})/2**23)*((-1)**(result[31]));
$display("Expected Value : %f Result : %f",-0.5+6.4,value);
#20
value =(2**(result[30:23]-127))*($itor({1'b1,result[22:0]})/2**23)*((-1)**(result[31]));
$display("Expected Value : %f Result : %f",2.82+(-0.94),value);


#20
$display("===== Subtraction =====");
value =(2**(result[30:23]-127))*($itor({1'b1,result[22:0]})/2**23)*((-1)**(result[31]));
$display("Expected Value : %f Result : %f",3.2-4.2,value);
#20
value =(2**(result[30:23]-127))*($itor({1'b1,result[22:0]})/2**23)*((-1)**(result[31]));
$display("Expected Value : %f Result : %f",0.66-0.51,value);
#20
value =(2**(result[30:23]-127))*($itor({1'b1,result[22:0]})/2**23)*((-1)**(result[31]));
$display("Expected Value : %f Result : %f",-0.5-(-6.4),value);
#20
value =(2**(result[30:23]-127))*($itor({1'b1,result[22:0]})/2**23)*((-1)**(result[31]));
$display("Expected Value : %f Result : %f",-0.5-6.4,value);
#20
value =(2**(result[30:23]-127))*($itor({1'b1,result[22:0]})/2**23)*((-1)**(result[31]));
$display("Expected Value : %f Result : %f",2.82-(-0.94),value);


#20
$display("===== Multiplication =====");
value =(2**(result[30:23]-127))*($itor({1'b1,result[22:0]})/2**23)*((-1)**(result[31]));
$display("Expected Value : %f Result : %f",3.2*4.2,value);
#20
value =(2**(result[30:23]-127))*($itor({1'b1,result[22:0]})/2**23)*((-1)**(result[31]));
$display("Expected Value : %f Result : %f",0.66*0.51,value);
#20
value =(2**(result[30:23]-127))*($itor({1'b1,result[22:0]})/2**23)*((-1)**(result[31]));
$display("Expected Value : %f Result : %f",-0.5*(-6.4),value);
#20
value =(2**(result[30:23]-127))*($itor({1'b1,result[22:0]})/2**23)*((-1)**(result[31]));
$display("Expected Value : %f Result : %f",-0.5*6.4,value);
#20
value =(2**(result[30:23]-127))*($itor({1'b1,result[22:0]})/2**23)*((-1)**(result[31]));
$display("Expected Value : %f Result : %f",2.82*(-0.94),value);


$display("===== Division =====");
#20
value =(2**(result[30:23]-127))*($itor({1'b1,result[22:0]})/2**23)*((-1)**(result[31]));
$display("Expected Value : %f Result : %f Hex Values : %h",4.2/3.2,value, result);
#20
value =(2**(result[30:23]-127))*($itor({1'b1,result[22:0]})/2**23)*((-1)**(result[31]));
$display("Expected Value : %f Result : %f Hex Values : %h",0.66/0.51,value, result);
#20
value =(2**(result[30:23]-127))*($itor({1'b1,result[22:0]})/2**23)*((-1)**(result[31]));
$display("Expected Value : %f Result : %f Hex Values : %h",(-6.4)/(-0.5),value, result);
#20
value =(2**(result[30:23]-127))*($itor({1'b1,result[22:0]})/2**23)*((-1)**(result[31]));
$display("Expected Value : %f Result : %f Hex Values : %h",(-0.5)/6.4,value, result);
#20
value =(2**(result[30:23]-127))*($itor({1'b1,result[22:0]})/2**23)*((-1)**(result[31]));
$display("Expected Value : %f Result : %f Hex Values : %h",2.82/(-0.94),value, result);

#20
$display("===== Sign Injection =====");
value =(2**(result[30:23]-127))*($itor({1'b1,result[22:0]})/2**23)*((-1)**(result[31]));
$display("Expected Value : %f Result : %f Hex Values : %h",0.5,value, result);
#20
value =(2**(result[30:23]-127))*($itor({1'b1,result[22:0]})/2**23)*((-1)**(result[31]));
$display("Expected Value : %f Result : %f Hex Values : %h",-0.5,value, result);


$finish;
end

endmodule

FPU/verification/FPU.vcd
$date
	Wed Jun 18 21:35:41 2025
$end
$version
	Icarus Verilog
$end
$timescale
	1ps
$end
$scope module FPU_tb $end
$var wire 32 ! result [31:0] $end
$var reg 32 " A [31:0] $end
$var reg 32 # B [31:0] $end
$var reg 3 $ fpu_control [2:0] $end
$var reg 1 % fpu_sel $end
$var reg 3 & funct3 [2:0] $end
$var real 1 ' value $end
$scope module dut $end
$var wire 3 ( fpu_control [2:0] $end
$var wire 1 % fpu_sel $end
$var wire 3 ) funct3 [2:0] $end
$var wire 32 * rs1 [31:0] $end
$var wire 32 + rs2 [31:0] $end
$var wire 1 , sign_temp $end
$var wire 32 - MulResult [31:0] $end
$var wire 32 . DivResult [31:0] $end
$var wire 32 / AddSubResult [31:0] $end
$var reg 32 0 fpu_result [31:0] $end
$scope module ASFPU_inst $end
$var wire 32 1 N1 [31:0] $end
$var wire 32 2 N2 [31:0] $end
$var wire 1 % sel $end
$var wire 32 3 result [31:0] $end
$var reg 8 4 E1 [7:0] $end
$var reg 8 5 E2 [7:0] $end
$var reg 32 6 N1_swap [31:0] $end
$var reg 32 7 N2_swap [31:0] $end
$var reg 24 8 S1 [23:0] $end
$var reg 24 9 S2 [23:0] $end
$var reg 1 : carry $end
$var reg 8 ; d [7:0] $end
$var reg 8 < exponent [7:0] $end
$var reg 1 = sign1 $end
$var reg 1 > sign2 $end
$var reg 24 ? temp_mantissa [23:0] $end
$var integer 32 @ i [31:0] $end
$upscope $end
$scope module DivFPUinst $end
$var wire 32 A N1 [31:0] $end
$var wire 32 B N2 [31:0] $end
$var wire 32 C result [31:0] $end
$var wire 1 D S2 $end
$var wire 1 E S1 $end
$var wire 8 F E2 [7:0] $end
$var wire 8 G E1 [7:0] $end
$var reg 9 H E [8:0] $end
$var reg 25 I M [24:0] $end
$var reg 24 J M1 [23:0] $end
$var reg 24 K M2 [23:0] $end
$var reg 1 L Sign $end
$var reg 8 M exponent [7:0] $end
$var reg 23 N mantissa [22:0] $end
$var reg 48 O raw_mant [47:0] $end
$var integer 32 P i [31:0] $end
$upscope $end
$scope module MulFPUinst $end
$var wire 32 Q N1 [31:0] $end
$var wire 32 R N2 [31:0] $end
$var wire 32 S result [31:0] $end
$var reg 9 T E [8:0] $end
$var reg 8 U E1 [7:0] $end
$var reg 8 V E2 [7:0] $end
$var reg 48 W M [47:0] $end
$var reg 24 X M1 [23:0] $end
$var reg 24 Y M2 [23:0] $end
$var reg 1 Z S1 $end
$var reg 1 [ S2 $end
$var reg 1 \ Sign $end
$var reg 8 ] exponent [7:0] $end
$var reg 23 ^ mantissa [22:0] $end
$var integer 32 _ i [31:0] $end
$upscope $end
$upscope $end
$upscope $end
$enddefinitions $end
$comment Show the parameter values. $end
$dumpall
$end
#0
$dumpvars
b0 _
b10101110000101000111011 ^
b10000010 ]
0\
0[
0Z
b100001100110011001100110 Y
b110011001100110011001100 X
b11010111000010100011101111110101110000101001000 W
b10000001 V
b10000000 U
b10000010 T
b1000001010101110000101000111011 S
b1000000100001100110011001100110 R
b1000000010011001100110011001100 Q
b0 P
b11001100110011001100110000000000000000000000000 O
b10000110000110000110000 N
b1111110 M
0L
b100001100110011001100110 K
b110011001100110011001100 J
b110000110000110000110000 I
b1111110 H
b10000000 G
b10000001 F
0E
0D
b111111010000110000110000110000 C
b1000000100001100110011001100110 B
b1000000010011001100110011001100 A
b0 @
b111011001100110011001100 ?
0>
0=
b10000001 <
b1 ;
0:
b11001100110011001100110 9
b100001100110011001100110 8
b1000000010011001100110011001100 7
b1000000100001100110011001100110 6
b10000001 5
b10000001 4
b1000000111011001100110011001100 3
b1000000100001100110011001100110 2
b1000000010011001100110011001100 1
b1000000111011001100110011001100 0
b1000000111011001100110011001100 /
b111111010000110000110000110000 .
b1000001010101110000101000111011 -
0,
b1000000100001100110011001100110 +
b1000000010011001100110011001100 *
bx )
b0 (
r0 '
bx &
0%
b0 $
b1000000100001100110011001100110 #
b1000000010011001100110011001100 "
b1000000111011001100110011001100 !
$end
#15000
r7.399999618530273 '
#20000
b10101000111101011100001100000000000000000000000 O
b111111100101011100001010001111 !
b111111100101011100001010001111 0
b1111110 F
1:
b101011100001010001111 ?
b111111100101011100001010001111 /
b111111100101011100001010001111 3
b1111111 <
b0 ;
b1111110 5
b1111110 4
b100000101000111101011100 9
b101010001111010111000011 8
b111111000000101000111101011100 7
b111111001010001111010111000011 6
b1001011010010110100110 N
b111111101001011010010110100110 .
b111111101001011010010110100110 C
b1111111 M
b101001011010010110100110 I
b1111111 H
b100000101000111101011100 K
b101010001111010111000011 J
b1111110 G
b1111101 ]
b111110101011000101011011010110 -
b111110101011000101011011010110 S
b1011000101011011010110 ^
b10101100010101101101011000001100011111100010100 W
b1111101 T
b1111110 V
b1111110 U
b100000101000111101011100 Y
b101010001111010111000011 X
b111111000000101000111101011100 #
b111111000000101000111101011100 +
b111111000000101000111101011100 2
b111111000000101000111101011100 B
b111111000000101000111101011100 R
b111111001010001111010111000011 "
b111111001010001111010111000011 *
b111111001010001111010111000011 1
b111111001010001111010111000011 A
b111111001010001111010111000011 Q
#35000
r1.169999957084656 '
#40000
b10000000000000000000000000000000000000000000000 O
b11000000110111001100110011001100 !
b11000000110111001100110011001100 0
b10000001 F
1D
0:
b110111001100110011001100 ?
b10000001 <
b10000001 5
b11 ;
b10000001 4
1>
b11000000110111001100110011001100 /
b11000000110111001100110011001100 3
1=
b100000000000000000000 9
b110011001100110011001100 8
b10111111000000000000000000000000 7
b11000000110011001100110011001100 6
b1000000000000000000000 N
b1111011 M
b1 P
b1111011 H
b101000000000000000000000 I
b110011001100110011001100 K
b100000000000000000000000 J
b111101101000000000000000000000 .
b111101101000000000000000000000 C
0L
1E
b10000000 ]
b1000000010011001100110011001100 -
b1000000010011001100110011001100 S
b10011001100110011001100 ^
b11001100110011001100110000000000000000000000000 W
b10000000 T
1[
1Z
b10000001 V
b110011001100110011001100 Y
b100000000000000000000000 X
b11000000110011001100110011001100 #
b11000000110011001100110011001100 +
b11000000110011001100110011001100 2
b11000000110011001100110011001100 B
b11000000110011001100110011001100 R
b10111111000000000000000000000000 "
b10111111000000000000000000000000 *
b10111111000000000000000000000000 1
b10111111000000000000000000000000 A
b10111111000000000000000000000000 Q
#55000
r-6.899999618530273 '
#60000
1,
b1000000101111001100110011001100 !
b1000000101111001100110011001100 0
b101111001100110011001100 ?
b10000001 5
b1000000101111001100110011001100 /
b1000000101111001100110011001100 3
0=
b100000000000000000000 9
b10111111000000000000000000000000 7
b1000000110011001100110011001100 6
b1 P
b101000000000000000000000 I
b1111011 H
b10111101101000000000000000000000 .
b10111101101000000000000000000000 C
1L
0D
b11000000010011001100110011001100 -
b11000000010011001100110011001100 S
1\
0[
b1000000110011001100110011001100 #
b1000000110011001100110011001100 +
b1000000110011001100110011001100 2
b1000000110011001100110011001100 B
b1000000110011001100110011001100 R
#75000
r5.899999618530273 '
#80000
b10110100101101001011010100000000000000000000000 O
b111111111100001111000011110010 !
b111111111100001111000011110010 0
b1111110 F
1D
b1 @
b111100001111000011110010 ?
b111111111100001111000011110010 /
b111111111100001111000011110010 3
b1111111 <
b10 ;
b10000000 5
b10000000 4
b1111000011110000111100 9
b101101001011010010110101 8
b10111111011100001111000011110001 7
b1000000001101001011010010110101 6
b10000000000000000000000 N
b10000000 M
b1 P
b110000000000000000000000 I
b10000000 H
b111100001111000011110001 K
b101101001011010010110101 J
b11000000010000000000000000000000 .
b11000000010000000000000000000000 C
1L
b10000000 G
0E
b11000000001010100001001101111101 -
b11000000001010100001001101111101 S
b1010100001001101111101 ^
b10101010000100110111110100110111110011100110010 W
b10000000 T
1[
0Z
b1111110 V
b10000000 U
b111100001111000011110001 Y
b101101001011010010110101 X
b10111111011100001111000011110001 #
b10111111011100001111000011110001 +
b10111111011100001111000011110001 2
b10111111011100001111000011110001 B
b10111111011100001111000011110001 R
b1000000001101001011010010110101 "
b1000000001101001011010010110101 *
b1000000001101001011010010110101 1
b1000000001101001011010010110101 A
b1000000001101001011010010110101 Q
#95000
r1.882353067398071 '
#100000
b11001100110011001100110000000000000000000000000 O
0,
0L
b10111111100000000000000000000000 !
b10111111100000000000000000000000 0
b10000001 F
0D
b10 @
1=
b100000000000000000000000 ?
b10111111100000000000000000000000 /
b10111111100000000000000000000000 3
b1111111 <
b10000001 5
b1 ;
b10000001 4
0>
b11001100110011001100110 9
b100001100110011001100110 8
b1000000010011001100110011001100 7
b1000000100001100110011001100110 6
b10000110000110000110000 N
b111111010000110000110000110000 .
b111111010000110000110000110000 C
b1111110 M
b0 P
b110000110000110000110000 I
b1111110 H
b100001100110011001100110 K
b110011001100110011001100 J
b10000010 ]
b10101110000101000111011 ^
b11010111000010100011101111110101110000101001000 W
b10000010 T
b1000001010101110000101000111011 -
b1000001010101110000101000111011 S
0\
0[
b10000001 V
b100001100110011001100110 Y
b110011001100110011001100 X
1%
b1 $
b1 (
b1000000100001100110011001100110 #
b1000000100001100110011001100110 +
b1000000100001100110011001100110 2
b1000000100001100110011001100110 B
b1000000100001100110011001100110 R
b1000000010011001100110011001100 "
b1000000010011001100110011001100 *
b1000000010011001100110011001100 1
b1000000010011001100110011001100 A
b1000000010011001100110011001100 Q
#115000
r-1 '
#120000
b10101000111101011100001100000000000000000000000 O
b111110000110011001100110011100 !
b111110000110011001100110011100 0
b1111110 F
b10 @
b100110011001100110011100 ?
b1111100 <
b0 ;
b1111110 5
b1111110 4
b111110000110011001100110011100 /
b111110000110011001100110011100 3
0=
b100000101000111101011100 9
b101010001111010111000011 8
b111111000000101000111101011100 7
b111111001010001111010111000011 6
b1001011010010110100110 N
b111111101001011010010110100110 .
b111111101001011010010110100110 C
b1111111 M
b101001011010010110100110 I
b1111111 H
b100000101000111101011100 K
b101010001111010111000011 J
b1111110 G
b1111101 ]
b111110101011000101011011010110 -
b111110101011000101011011010110 S
b1011000101011011010110 ^
b10101100010101101101011000001100011111100010100 W
b1111101 T
b1111110 V
b1111110 U
b100000101000111101011100 Y
b101010001111010111000011 X
b111111000000101000111101011100 #
b111111000000101000111101011100 +
b111111000000101000111101011100 2
b111111000000101000111101011100 B
b111111000000101000111101011100 R
b111111001010001111010111000011 "
b111111001010001111010111000011 *
b111111001010001111010111000011 1
b111111001010001111010111000011 A
b111111001010001111010111000011 Q
#135000
r0 '
#140000
b10000000000000000000000000000000000000000000000 O
b1000000101111001100110011001100 !
b1000000101111001100110011001100 0
b10000001 F
1D
b0 @
b101111001100110011001100 ?
b10000001 <
b10000001 5
b11 ;
b10000001 4
1>
b1000000101111001100110011001100 /
b1000000101111001100110011001100 3
0=
b100000000000000000000 9
b110011001100110011001100 8
b10111111000000000000000000000000 7
b11000000110011001100110011001100 6
b1000000000000000000000 N
b1111011 M
b1 P
b1111011 H
b101000000000000000000000 I
b110011001100110011001100 K
b100000000000000000000000 J
b111101101000000000000000000000 .
b111101101000000000000000000000 C
0L
1E
b10000000 ]
b1000000010011001100110011001100 -
b1000000010011001100110011001100 S
b10011001100110011001100 ^
b11001100110011001100110000000000000000000000000 W
b10000000 T
1[
1Z
b10000001 V
b110011001100110011001100 Y
b100000000000000000000000 X
b11000000110011001100110011001100 #
b11000000110011001100110011001100 +
b11000000110011001100110011001100 2
b11000000110011001100110011001100 B
b11000000110011001100110011001100 R
b10111111000000000000000000000000 "
b10111111000000000000000000000000 *
b10111111000000000000000000000000 1
b10111111000000000000000000000000 A
b10111111000000000000000000000000 Q
#155000
r5.899999618530273 '
#160000
1,
b11000000110111001100110011001100 !
b11000000110111001100110011001100 0
b11000000110111001100110011001100 /
b11000000110111001100110011001100 3
1=
b110111001100110011001100 ?
b10000001 5
b100000000000000000000 9
b10111111000000000000000000000000 7
b1000000110011001100110011001100 6
b1 P
b101000000000000000000000 I
b1111011 H
b10111101101000000000000000000000 .
b10111101101000000000000000000000 C
1L
0D
b11000000010011001100110011001100 -
b11000000010011001100110011001100 S
1\
0[
b1000000110011001100110011001100 #
b1000000110011001100110011001100 +
b1000000110011001100110011001100 2
b1000000110011001100110011001100 B
b1000000110011001100110011001100 R
#175000
r-6.899999618530273 '
#180000
b10110100101101001011010100000000000000000000000 O
b1000000011100001111000011110001 !
b1000000011100001111000011110001 0
b1111110 F
1D
b111100001111000011110001 ?
b10000000 <
b10 ;
b10000000 5
b10000000 4
b1000000011100001111000011110001 /
b1000000011100001111000011110001 3
0=
b1111000011110000111100 9
b101101001011010010110101 8
b10111111011100001111000011110001 7
b1000000001101001011010010110101 6
b10000000000000000000000 N
b10000000 M
b1 P
b110000000000000000000000 I
b10000000 H
b111100001111000011110001 K
b101101001011010010110101 J
b11000000010000000000000000000000 .
b11000000010000000000000000000000 C
1L
b10000000 G
0E
b11000000001010100001001101111101 -
b11000000001010100001001101111101 S
b1010100001001101111101 ^
b10101010000100110111110100110111110011100110010 W
b10000000 T
1[
0Z
b1111110 V
b10000000 U
b111100001111000011110001 Y
b101101001011010010110101 X
b10111111011100001111000011110001 #
b10111111011100001111000011110001 +
b10111111011100001111000011110001 2
b10111111011100001111000011110001 B
b10111111011100001111000011110001 R
b1000000001101001011010010110101 "
b1000000001101001011010010110101 *
b1000000001101001011010010110101 1
b1000000001101001011010010110101 A
b1000000001101001011010010110101 Q
#195000
r3.764705896377563 '
#200000
b11001100110011001100110000000000000000000000000 O
0,
0L
b10000001 F
0D
b10 @
1=
b100000000000000000000000 ?
b10111111100000000000000000000000 /
b10111111100000000000000000000000 3
b1111111 <
b10000001 5
b1 ;
b10000001 4
0>
b11001100110011001100110 9
b100001100110011001100110 8
b1000000010011001100110011001100 7
b1000000100001100110011001100110 6
b10000110000110000110000 N
b111111010000110000110000110000 .
b111111010000110000110000110000 C
b1111110 M
b0 P
b110000110000110000110000 I
b1111110 H
b100001100110011001100110 K
b110011001100110011001100 J
b10000010 ]
b10101110000101000111011 ^
b11010111000010100011101111110101110000101001000 W
b10000010 T
b1000001010101110000101000111011 -
b1000001010101110000101000111011 S
0\
0[
b10000001 V
b100001100110011001100110 Y
b110011001100110011001100 X
b1000001010101110000101000111011 !
b1000001010101110000101000111011 0
b10 $
b10 (
b1000000100001100110011001100110 #
b1000000100001100110011001100110 +
b1000000100001100110011001100110 2
b1000000100001100110011001100110 B
b1000000100001100110011001100110 R
b1000000010011001100110011001100 "
b1000000010011001100110011001100 *
b1000000010011001100110011001100 1
b1000000010011001100110011001100 A
b1000000010011001100110011001100 Q
#215000
r13.43999767303467 '
#220000
b10101000111101011100001100000000000000000000000 O
b111110101011000101011011010110 !
b111110101011000101011011010110 0
b1111110 F
b10 @
b100110011001100110011100 ?
b1111100 <
b0 ;
b1111110 5
b1111110 4
b111110000110011001100110011100 /
b111110000110011001100110011100 3
0=
b100000101000111101011100 9
b101010001111010111000011 8
b111111000000101000111101011100 7
b111111001010001111010111000011 6
b1001011010010110100110 N
b111111101001011010010110100110 .
b111111101001011010010110100110 C
b1111111 M
b101001011010010110100110 I
b1111111 H
b100000101000111101011100 K
b101010001111010111000011 J
b1111110 G
b1111101 ]
b111110101011000101011011010110 -
b111110101011000101011011010110 S
b1011000101011011010110 ^
b10101100010101101101011000001100011111100010100 W
b1111101 T
b1111110 V
b1111110 U
b100000101000111101011100 Y
b101010001111010111000011 X
b111111000000101000111101011100 #
b111111000000101000111101011100 +
b111111000000101000111101011100 2
b111111000000101000111101011100 B
b111111000000101000111101011100 R
b111111001010001111010111000011 "
b111111001010001111010111000011 *
b111111001010001111010111000011 1
b111111001010001111010111000011 A
b111111001010001111010111000011 Q
#235000
r0 '
