RV32IMFcore/DivFPU_Flowchart.v
module DivFPU_Flowchart (
    input  [31:0] N1,
    input  [31:0] N2,
    output [31:0] result
);

    // Internal variables
    reg [23:0] M1, M2;
    reg [24:0] M;        // Mantissa result after division
    reg [8:0] E;
    reg [47:0] raw_mant;
    reg [22:0] mantissa;
    reg [7:0] exponent;
    reg Sign;
    wire [7:0] E1, E2;
    wire S1, S2;
    integer i;

    assign E1 = N1[30:23];
    assign E2 = N2[30:23];
    assign S1 = N1[31];
    assign S2 = N2[31];

    always @(*) begin
        // Step 1: Compute Sign
        Sign = S1 ^ S2;

        // Step 2: Extract mantissas with hidden bit
        M1 = {1'b1, N1[22:0]};
        M2 = {1'b1, N2[22:0]};

        // Step 3: Subtract exponents and add bias
        E = E1 - E2 + 127;

        // Step 4: Fixed-point division (scaled)
        raw_mant <= {M1,23'b0};
        M = raw_mant / M2;  // 47-bit numerator


        // Step 5: Zero check
        if (M == 0) begin
            E = 8'd0;
            mantissa = 23'd0;
        end else begin
            if (M[24]) begin
                M = M >> 1;
                E = E + 1;
            end
            // Step 6: Normalize using a for loop
            else begin
            for (i = 0;!M[23] && E > 0 && i < 23; i = i + 1) begin
                M = M << 1;
                E = E - 1;
            end
            end

            // Step 7: Check for exponent overflow
            if (E[8]) begin
                exponent = 8'hFF;
                mantissa = 23'd0;
            end else begin
                exponent = E[7:0];
                mantissa = M; // Extract top 23 bits
            end
        end
    end

    assign result = {Sign, exponent, mantissa};

endmodule

FPU/tb/DivFPU_Flowchart_tb.v
`include "../src/DivFPU_Flowchart.v"

module DivFPU_Flowchart_tb;
reg [31:0] A,B;
wire [31:0] result;
real  value; 
DivFPU_Flowchart dut (
    .N1(A),
    .N2(B),
    .result(result)
);

initial  
begin
        $dumpfile("DivFPU_Flowchart.vcd");
        $dumpvars(0,DivFPU_Flowchart_tb);
A = 32'b0_10000000_10011001100110011001100;  // 3.2
B = 32'b0_10000001_00001100110011001100110;  // 4.2
#20
A = 32'b0_01111011_10011001100110011001101;
B = 32'b0_01111011_10011001100110011001101;
/*A = 32'b0_01111110_01010001111010111000011;  // 0.66
B = 32'b0_01111110_00000101000111101011100;  // 0.51*/
#20
A = 32'b1_01111110_00000000000000000000000;  // -0.5
B = 32'b1_10000001_10011001100110011001100;  // -6.4
#20
A = 32'b1_01111110_00000000000000000000000;  // -0.5
B = 32'b0_10000001_10011001100110011001100;  //  6.4
#20
A = 32'h4034b4b5;
B = 32'hbf70f0f1;
#20
A=32'b01000000000000000000000000000000;
B=32'b01000000010000000000000000000000;
end

initial
begin
#15
value =(2**(result[30:23]-127))*($itor({1'b1,result[22:0]})/2**23)*((-1)**(result[31]));
$display("Expected Value : %f Result : %f Hex Value : %h",3.2/4.2,value, result);
#20
value =(2**(result[30:23]-127))*($itor({1'b1,result[22:0]})/2**23)*((-1)**(result[31]));
$display("Expected Value : %f Result : %f Hex Value : %h",0.1/0.1,value, result);
#20
value =(2**(result[30:23]-127))*($itor({1'b1,result[22:0]})/2**23)*((-1)**(result[31]));
$display("Expected Value : %f Result : %f Hex Value : %h",-0.5/(-6.4),value, result);
#20
value =(2**(result[30:23]-127))*($itor({1'b1,result[22:0]})/2**23)*((-1)**(result[31]));
$display("Expected Value : %f Result : %f Hex Value : %h",-0.5/6.4,value, result);
#20
value =(2**(result[30:23]-127))*($itor({1'b1,result[22:0]})/2**23)*((-1)**(result[31]));
$display("Expected Value : %f Result : %f Hex Value : %h",2.82/(-0.94),value, result);
#20
value =(2**(result[30:23]-127))*($itor({1'b1,result[22:0]})/2**23)*((-1)**(result[31]));
$display("Expected Value : %f Result : %f Hex Value : %h",2/(3),value, result);
$finish;
end

endmodule

FPU/tb/DivFPU_Flowchart.vcd
$date
	Thu Jun 05 18:37:23 2025
$end
$version
	Icarus Verilog
$end
$timescale
	1s
$end
$scope module DivFPU_Flowchart_tb $end
$var wire 32 ! result [31:0] $end
$var reg 32 " A [31:0] $end
$var reg 32 # B [31:0] $end
$var real 1 $ value $end
$scope module dut $end
$var wire 32 % N1 [31:0] $end
$var wire 32 & N2 [31:0] $end
$var wire 32 ' result [31:0] $end
$var wire 1 ( S2 $end
$var wire 1 ) S1 $end
$var wire 8 * E2 [7:0] $end
$var wire 8 + E1 [7:0] $end
$var reg 9 , E [8:0] $end
$var reg 25 - M [24:0] $end
$var reg 24 . M1 [23:0] $end
$var reg 24 / M2 [23:0] $end
$var reg 1 0 Sign $end
$var reg 8 1 exponent [7:0] $end
$var reg 23 2 mantissa [22:0] $end
$var reg 48 3 raw_mant [47:0] $end
$var integer 32 4 i [31:0] $end
$upscope $end
$upscope $end
$enddefinitions $end
$comment Show the parameter values. $end
$dumpall
$end
#0
$dumpvars
b0 4
b11001100110011001100110000000000000000000000000 3
b10000110000110000110000 2
b1111110 1
00
b100001100110011001100110 /
b110011001100110011001100 .
b110000110000110000110000 -
b1111110 ,
b10000000 +
b10000001 *
0)
0(
b111111010000110000110000110000 '
b1000000100001100110011001100110 &
b1000000010011001100110011001100 %
r0 $
b1000000100001100110011001100110 #
b1000000010011001100110011001100 "
b111111010000110000110000110000 !
$end
#20
b11001100110011001100110100000000000000000000000 3
b1111011 *
b0 2
b111111100000000000000000000000 !
b111111100000000000000000000000 '
b1111111 1
b0 4
b100000000000000000000000 -
b1111111 ,
b110011001100110011001101 /
b110011001100110011001101 .
b1111011 +
b111101110011001100110011001101 #
b111101110011001100110011001101 &
b111101110011001100110011001101 "
b111101110011001100110011001101 %
#35
r1 $
#40
b1000000000000000000000 2
b1 4
b101000000000000000000000 -
b10000000000000000000000000000000000000000000000 3
b10000001 *
1(
b1111011 1
b1111011 ,
b110011001100110011001100 /
b100000000000000000000000 .
b111101101000000000000000000000 !
b111101101000000000000000000000 '
00
b1111110 +
1)
b11000000110011001100110011001100 #
b11000000110011001100110011001100 &
b10111111000000000000000000000000 "
b10111111000000000000000000000000 %
#55
r0 $
#60
b1 4
b101000000000000000000000 -
b1111011 ,
b10111101101000000000000000000000 !
b10111101101000000000000000000000 '
10
0(
b1000000110011001100110011001100 #
b1000000110011001100110011001100 &
#75
r-0 $
#80
b10110100101101001011010100000000000000000000000 3
b1111110 *
1(
b10000000000000000000000 2
b10000000 1
b1 4
b110000000000000000000000 -
b10000000 ,
b111100001111000011110001 /
b101101001011010010110101 .
b11000000010000000000000000000000 !
b11000000010000000000000000000000 '
10
b10000000 +
0)
b10111111011100001111000011110001 #
b10111111011100001111000011110001 &
b1000000001101001011010010110101 "
b1000000001101001011010010110101 %
#95
r-3 $
#100
b10000000000000000000000000000000000000000000000 3
b1111110 1
00
b10000000 *
0(
b111111001010101010101010101010 !
b111111001010101010101010101010 '
b1010101010101010101010 2
b1 4
b101010101010101010101010 -
b1111110 ,
b110000000000000000000000 /
b100000000000000000000000 .
b1000000010000000000000000000000 #
b1000000010000000000000000000000 &
b1000000000000000000000000000000 "
b1000000000000000000000000000000 %
#115
r0 $
